[
    {
        "category": "Fútbol Americano NCAA",
        "title": "Alabama vs Indiana (Cuartos de Final #3)",
        "subtitle": "Fútbol Americano NCAA",
        "time": "18:00",
        "channel_name": "ESPN 3 AR",
        "channel_logo_url": "https://imagenes.gatotv.com/logos/canales/claros/espn_3_norte-mediano.png",
        "target_channel_name": "ESPN 3 AR"
    },
    {
        "category": "Baloncesto",
        "title": "Detroit Pistons vs Miami Heat",
        "subtitle": "NBA",
        "time": "21:00",
        "channel_name": "NBA",
        "channel_logo_url": "https://bestleague.world/img/nba.svg",
        "target_channel_name": "NBA"
    }
]