[
    {
        "title": "Gimnasia (M) vs Central Córdoba",
        "time": "16:45",
        "subtitle": "Torneo Clausura",
        "channel_name": "TNT Sports AR (FL)",
        "target_channel_name": "TNT Sports AR (FL)",
        "channel_logo_url": "https://imagenes.gatotv.com/logos/canales/claros/tnt_sports-mediano.png",
        "home_logo": "https://r2.thesportsdb.com/images/media/team/badge/h11mlf1677636958.png/small",
        "away_logo": "https://r2.thesportsdb.com/images/media/team/badge/d62xkc1576101576.png",
        "category": "Fútbol"
    },
    {
        "category": "Fútbol",
        "title": "Racing vs Gimnasia (LP)",
        "subtitle": "Torneo Clausura",
        "time": "19:00",
        "channel_name": "ESPN Premium",
        "channel_logo_url": "https://imagenes.gatotv.com/logos/canales/claros/espn_premium-mediano.png",
        "target_channel_name": "ESPN Premium",
        "home_logo": "https://r2.thesportsdb.com/images/media/team/badge/vi4mu41695734959.png",
        "away_logo": "https://r2.thesportsdb.com/images/media/team/badge/ksqyvk1517768491.png"
    },
    {
        "category": "Fútbol",
        "title": "Vélez vs Instituto",
        "subtitle": "Torneo Clausura",
        "time": "19:00",
        "channel_name": "TNT Sports AR (FL)",
        "channel_logo_url": "https://imagenes.gatotv.com/logos/canales/claros/tnt_sports-mediano.png",
        "target_channel_name": "TNT Sports AR (FL)",
        "home_logo": "https://r2.thesportsdb.com/images/media/team/badge/jo98m71517769587.png",
        "away_logo": "https://r2.thesportsdb.com/images/media/team/badge/jup59w1578825794.png"
    },
    {
        "category": "Fútbol",
        "title": "Huracán vs Banfield",
        "subtitle": "Torneo Clausura",
        "time": "21:15",
        "channel_name": "ESPN AR",
        "channel_logo_url": "https://imagenes.gatotv.com/logos/canales/claros/espn_norte-mediano.png",
        "target_channel_name": "ESPN AR",
        "home_logo": "https://r2.thesportsdb.com/images/media/team/badge/3cafun1580842587.png",
        "away_logo": "https://r2.thesportsdb.com/images/media/team/badge/udyvv91517768017.png"
    },
    {
        "category": "Fútbol",
        "title": "Platense vs Unión",
        "subtitle": "Torneo Clausura",
        "time": "21:15",
        "channel_name": "TNT Sports AR (FL)",
        "channel_logo_url": "https://imagenes.gatotv.com/logos/canales/claros/tnt_sports-mediano.png",
        "target_channel_name": "TNT Sports AR (FL)",
        "home_logo": "https://r2.thesportsdb.com/images/media/team/badge/lbs14n1769317149.png",
        "away_logo": "https://r2.thesportsdb.com/images/media/team/badge/btnx6q1734587495.png"
    },
    {
        "title": "2 de Mayo vs Rubio Ñú",
        "time": "16:00",
        "subtitle": "Primera Paraguay",
        "channel_name": "Eventos Tigo",
        "target_channel_name": "Eventos Tigo",
        "channel_logo_url": "https://i.ibb.co/4nmmZmXD/330px-Tigo-Sports-2025.png",
        "home_logo": "https://r2.thesportsdb.com/images/media/team/badge/1xw1cj1705639376.png",
        "away_logo": "https://r2.thesportsdb.com/images/media/team/badge/49iqvp1611773192.png/small",
        "category": "Fútbol"
    },
    {
        "title": "Cerro Porteño vs Trinidense",
        "time": "18:30",
        "subtitle": "Primera Paraguay",
        "channel_name": "Eventos Tigo",
        "target_channel_name": "Eventos Tigo",
        "channel_logo_url": "https://i.ibb.co/4nmmZmXD/330px-Tigo-Sports-2025.png",
        "home_logo": "https://r2.thesportsdb.com/images/media/team/badge/xkxqtz1652126507.png",
        "away_logo": "https://r2.thesportsdb.com/images/media/team/badge/oi8bxo1766423607.png",
        "category": "Fútbol"
    }
]