[
    {
        "title": "GP Bélgica - Prácticas Libres #1",
        "time": "08:30",
        "subtitle": "Fórmula 1",
        "channel_name": "Fox Sports AR",
        "target_channel_name": "Fox Sports AR",
        "channel_logo_url": "https://bestleague.world/img/foxnew.png",
        "home_logo": "https://r2.thesportsdb.com/images/media/league/logo/jiqa741556460666.png",
        "away_logo": "",
        "category": "Automovilismo"
    },
    {
        "title": "GP Bélgica - Prácticas Libres #2 ",
        "time": "12:00",
        "subtitle": "Fórmula 1",
        "channel_name": "Fox Sports AR",
        "target_channel_name": "Fox Sports AR",
        "channel_logo_url": "https://bestleague.world/img/foxnew.png",
        "home_logo": "https://r2.thesportsdb.com/images/media/league/logo/jiqa741556460666.png",
        "away_logo": "",
        "category": "Automovilismo"
    },
    {
        "title": "San Lorenzo vs Deportivo Riestra",
        "time": "18:45",
        "subtitle": "Copa Argentina",
        "channel_name": "TyC Sports HD",
        "target_channel_name": "TyC Sports HD",
        "channel_logo_url": "https://i.ibb.co/Fqjhk1TJ/960px-Ty-C-Sports-Logo-svg.png",
        "home_logo": "https://r2.thesportsdb.com/images/media/team/badge/qr7ose1517769136.png",
        "away_logo": "https://r2.thesportsdb.com/images/media/team/badge/332h0l1578824392.png",
        "category": "Fútbol"
    },
    {
        "title": "River Plate vs Aldosivi",
        "time": "00:00",
        "subtitle": "Copa Argentina",
        "channel_name": "TyC Sports HD",
        "target_channel_name": "TyC Sports HD",
        "channel_logo_url": "https://i.ibb.co/Fqjhk1TJ/960px-Ty-C-Sports-Logo-svg.png",
        "home_logo": "https://r2.thesportsdb.com/images/media/team/badge/03dmi31645539717.png",
        "away_logo": "https://r2.thesportsdb.com/images/media/team/badge/nqrjqb1517767667.png",
        "category": "Fútbol"
    },
    {
        "title": "Joel Mafauad vs. Elias Hidalgo",
        "time": "22:00",
        "subtitle": "ESPN KO",
        "channel_name": "ESPN 2",
        "target_channel_name": "ESPN 2 AR",
        "channel_logo_url": "https://imagenes.gatotv.com/logos/canales/claros/espn_2_norte-mediano.png",
        "home_logo": "https://bestleague.world/img/box.png",
        "away_logo": "",
        "category": "Fútbol"
    }
]